<?xml version="1.0" encoding="UTF-8"?>
<!DOCTYPE Characteristic>
<Characteristic version="1.0">
    <Name>7746Config</Name>
    <Uuid BaseUUID="000000001212EFDE1523785FEABCD123" BaseUUIDName="Nordic DFU Base UUID">3457</Uuid>
    <Value>000000000000000000000000</Value>
    <UsePresentationFormat>0</UsePresentationFormat>
    <MaxDataLength>12</MaxDataLength>
    <AttributeLenType>1</AttributeLenType>
    <Descriptor Value="0000" Exponent="0" Format="1" NameSpace="01" Unit="0000"/>
</Characteristic>
